<?xml version="1.0" encoding="UTF-8"?>
<feature
      id="org.eclipse.birt.nl"
      label="%featureName"
      version="2.3.0.qualifier"
      provider-name="%providerName"
      image="eclipse_update_120.jpg">

   <description url="http://www.eclipse.org/birt">
      %description
   </description>

   <copyright url="%copyrightURL">
      %copyright
   </copyright>

   <license url="%licenseURL">
      %license
   </license>

   <url>
      <update label="Business Intelligence and Reporting Tools (BIRT) Updates" url="http://download.eclipse.org/birt/update-site/2.3"/>
      <discovery label="%updateSiteName" url="http://download.eclipse.org/birt/update-site/2.3"/>
   </url>

   <plugin
         id="org.eclipse.birt.chart.device.extension.nl"
         download-size="0"
         install-size="0"
         version="0.0.0"
         fragment="true"
         unpack="false"/>

   <plugin
         id="org.eclipse.birt.chart.device.svg.nl"
         download-size="0"
         install-size="0"
         version="0.0.0"
         fragment="true"
         unpack="false"/>

   <plugin
         id="org.eclipse.birt.chart.device.swt.nl"
         download-size="0"
         install-size="0"
         version="0.0.0"
         fragment="true"
         unpack="false"/>

   <plugin
         id="org.eclipse.birt.chart.engine.extension.nl"
         download-size="0"
         install-size="0"
         version="0.0.0"
         fragment="true"
         unpack="false"/>

   <plugin
         id="org.eclipse.birt.chart.engine.nl"
         download-size="0"
         install-size="0"
         version="0.0.0"
         fragment="true"
         unpack="false"/>

   <plugin
         id="org.eclipse.birt.chart.reportitem.nl"
         download-size="0"
         install-size="0"
         version="0.0.0"
         fragment="true"
         unpack="false"/>

   <plugin
         id="org.eclipse.birt.chart.reportitem.ui.nl"
         download-size="0"
         install-size="0"
         version="0.0.0"
         fragment="true"
         unpack="false"/>

   <plugin
         id="org.eclipse.birt.resources.nl"
         download-size="0"
         install-size="0"
         version="0.0.0"
         fragment="true"
         unpack="false"/>

   <plugin
         id="org.eclipse.birt.chart.ui.extension.nl"
         download-size="0"
         install-size="0"
         version="0.0.0"
         fragment="true"
         unpack="false"/>

   <plugin
         id="org.eclipse.birt.core.nl"
         download-size="0"
         install-size="0"
         version="0.0.0"
         fragment="true"
         unpack="false"/>

   <plugin
         id="org.eclipse.birt.core.ui.nl"
         download-size="0"
         install-size="0"
         version="0.0.0"
         fragment="true"
         unpack="false"/>

   <plugin
         id="org.eclipse.birt.data.nl"
         download-size="0"
         install-size="0"
         version="0.0.0"
         fragment="true"
         unpack="false"/>

   <plugin
         id="org.eclipse.birt.chart.ui.nl"
         download-size="0"
         install-size="0"
         version="0.0.0"
         fragment="true"
         unpack="false"/>

   <plugin
         id="org.eclipse.birt.report.data.oda.jdbc.nl"
         download-size="0"
         install-size="0"
         version="0.0.0"
         fragment="true"
         unpack="false"/>

   <plugin
         id="org.eclipse.birt.report.data.oda.jdbc.ui.nl"
         download-size="0"
         install-size="0"
         version="0.0.0"
         fragment="true"
         unpack="false"/>

   <plugin
         id="org.eclipse.birt.report.data.oda.sampledb.nl"
         download-size="0"
         install-size="0"
         version="0.0.0"
         fragment="true"
         unpack="false"/>

   <plugin
         id="org.eclipse.birt.report.data.oda.sampledb.ui.nl"
         download-size="0"
         install-size="0"
         version="0.0.0"
         fragment="true"
         unpack="false"/>

   <plugin
         id="org.eclipse.birt.report.data.oda.xml.nl"
         download-size="0"
         install-size="0"
         version="0.0.0"
         fragment="true"
         unpack="false"/>

   <plugin
         id="org.eclipse.birt.report.debug.ui.nl"
         download-size="0"
         install-size="0"
         version="0.0.0"
         fragment="true"
         unpack="false"/>

   <plugin
         id="org.eclipse.birt.report.designer.core.nl"
         download-size="0"
         install-size="0"
         version="0.0.0"
         fragment="true"
         unpack="false"/>

   <plugin
         id="org.eclipse.birt.report.designer.ui.editors.schematic.nl"
         download-size="0"
         install-size="0"
         version="0.0.0"
         fragment="true"
         unpack="false"/>

   <plugin
         id="org.eclipse.birt.report.designer.ui.ide.nl"
         download-size="0"
         install-size="0"
         version="0.0.0"
         fragment="true"
         unpack="false"/>

   <plugin
         id="org.eclipse.birt.report.designer.ui.lib.explorer.nl"
         download-size="0"
         install-size="0"
         version="0.0.0"
         fragment="true"
         unpack="false"/>

   <plugin
         id="org.eclipse.birt.report.designer.ui.lib.nl"
         download-size="0"
         install-size="0"
         version="0.0.0"
         fragment="true"
         unpack="false"/>

   <plugin
         id="org.eclipse.birt.report.designer.ui.nl"
         download-size="0"
         install-size="0"
         version="0.0.0"
         fragment="true"
         unpack="false"/>

   <plugin
         id="org.eclipse.birt.report.designer.ui.preview.nl"
         download-size="0"
         install-size="0"
         version="0.0.0"
         fragment="true"
         unpack="false"/>

   <plugin
         id="org.eclipse.birt.report.designer.ui.rcp.nl"
         download-size="0"
         install-size="0"
         version="0.0.0"
         fragment="true"
         unpack="false"/>

   <plugin
         id="org.eclipse.birt.report.engine.nl"
         download-size="0"
         install-size="0"
         version="0.0.0"
         fragment="true"
         unpack="false"/>

   <plugin
         id="org.eclipse.birt.report.model.nl"
         download-size="0"
         install-size="0"
         version="0.0.0"
         fragment="true"
         unpack="false"/>

   <plugin
         id="org.eclipse.birt.report.viewer.nl"
         download-size="0"
         install-size="0"
         version="0.0.0"
         fragment="true"
         unpack="false"/>

   <plugin
         id="org.eclipse.birt.integration.wtp.ui.nl"
         download-size="0"
         install-size="0"
         version="0.0.0"
         fragment="true"
         unpack="false"/>

   <plugin
         id="org.eclipse.birt.report.item.crosstab.core.nl"
         download-size="0"
         install-size="0"
         version="0.0.0"
         fragment="true"
         unpack="false"/>

   <plugin
         id="org.eclipse.birt.report.item.crosstab.ui.nl"
         download-size="0"
         install-size="0"
         version="0.0.0"
         fragment="true"
         unpack="false"/>

   <plugin
         id="org.eclipse.birt.report.designer.ui.editor.xml.wtp.nl"
         download-size="0"
         install-size="0"
         version="0.0.0"
         fragment="true"
         unpack="false"/>

   <plugin
         id="org.eclipse.birt.report.designer.ui.views.nl"
         download-size="0"
         install-size="0"
         version="0.0.0"
         fragment="true"
         unpack="false"/>

   <plugin
         id="org.eclipse.birt.report.data.adapter.nl"
         download-size="0"
         install-size="0"
         version="0.0.0"
         fragment="true"
         unpack="false"/>

   <plugin
         id="org.eclipse.birt.report.designer.ui.samplesview.nl"
         download-size="0"
         install-size="0"
         version="0.0.0"
         fragment="true"
         unpack="false"/>

   <plugin
         id="org.eclipse.birt.report.designer.ui.preview.web.nl"
         download-size="0"
         install-size="0"
         version="0.0.0"
         fragment="true"
         unpack="false"/>

   <plugin
         id="org.eclipse.birt.report.designer.ui.cubebuilder.nl"
         download-size="0"
         install-size="0"
         version="0.0.0"
         fragment="true"
         unpack="false"/>

   <plugin
         id="org.eclipse.birt.chart.integration.wtp.ui.nl"
         download-size="0"
         install-size="0"
         version="0.0.0"
         fragment="true"
         unpack="false"/>

   <plugin
         id="org.eclipse.birt.chart.examples.nl"
         download-size="0"
         install-size="0"
         version="0.0.0"
         fragment="true"
         unpack="false"/>

   <plugin
         id="org.eclipse.datatools.connectivity.nl"
         download-size="0"
         install-size="0"
         version="0.0.0"
         fragment="true"
         unpack="false"/>

   <plugin
         id="org.eclipse.datatools.connectivity.oda.consumer.nl"
         download-size="0"
         install-size="0"
         version="0.0.0"
         fragment="true"
         unpack="false"/>

   <plugin
         id="org.eclipse.datatools.connectivity.oda.design.nl"
         download-size="0"
         install-size="0"
         version="0.0.0"
         fragment="true"
         unpack="false"/>

   <plugin
         id="org.eclipse.datatools.connectivity.oda.design.ui.nl"
         download-size="0"
         install-size="0"
         version="0.0.0"
         fragment="true"
         unpack="false"/>

   <plugin
         id="org.eclipse.datatools.connectivity.oda.flatfile.nl"
         download-size="0"
         install-size="0"
         version="0.0.0"
         fragment="true"
         unpack="false"/>

   <plugin
         id="org.eclipse.datatools.connectivity.oda.flatfile.ui.nl"
         download-size="0"
         install-size="0"
         version="0.0.0"
         fragment="true"
         unpack="false"/>

   <plugin
         id="org.eclipse.datatools.connectivity.oda.nl"
         download-size="0"
         install-size="0"
         version="0.0.0"
         fragment="true"
         unpack="false"/>

   <plugin
         id="org.eclipse.datatools.connectivity.oda.profile.nl"
         download-size="0"
         install-size="0"
         version="0.0.0"
         fragment="true"
         unpack="false"/>

   <plugin
         id="org.eclipse.datatools.connectivity.ui.dse.nl"
         download-size="0"
         install-size="0"
         version="0.0.0"
         fragment="true"
         unpack="false"/>

   <plugin
         id="org.eclipse.datatools.connectivity.ui.nl"
         download-size="0"
         install-size="0"
         version="0.0.0"
         fragment="true"
         unpack="false"/>

   <plugin
         id="org.eclipse.datatools.connectivity.oda.template.ui.nl"
         download-size="0"
         install-size="0"
         version="0.0.0"
         fragment="true"
         unpack="false"/>

   <plugin
         id="org.eclipse.datatools.enablement.oda.xml.nl"
         download-size="0"
         install-size="0"
         version="0.0.0"
         fragment="true"
         unpack="false"/>

   <plugin
         id="org.eclipse.datatools.enablement.oda.xml.ui.nl"
         download-size="0"
         install-size="0"
         version="0.0.0"
         fragment="true"
         unpack="false"/>

   <plugin
         id="org.eclipse.datatools.enablement.oda.ws.nl"
         download-size="0"
         install-size="0"
         version="0.0.0"
         fragment="true"
         unpack="false"/>

   <plugin
         id="org.eclipse.datatools.enablement.oda.ws.ui.nl"
         download-size="0"
         install-size="0"
         version="0.0.0"
         fragment="true"
         unpack="false"/>

   <plugin
         id="org.eclipse.birt.report.engine.dataextraction.csv.nl"
         download-size="0"
         install-size="0"
         version="0.0.0"
         fragment="true"
         unpack="false"/>

   <plugin
         id="org.eclipse.birt.data.aggregation.nl"
         download-size="0"
         install-size="0"
         version="0.0.0"
         fragment="true"
         unpack="false"/>
         
   <plugin
         id="org.eclipse.birt.report.designer.ui.editor.script.nl"
         download-size="0"
         install-size="0"
         version="0.0.0"
         fragment="true"
         unpack="false"/>
   
   <plugin
         id="org.eclipse.birt.report.data.oda.jdbc.dbprofile.nl"
         download-size="0"
         install-size="0"
         version="0.0.0"
         fragment="true"
         unpack="false"/>
   
   <plugin
         id="org.eclipse.birt.report.data.oda.jdbc.dbprofile.ui.nl"
         download-size="0"
         install-size="0"
         version="0.0.0"
         fragment="true"
         unpack="false"/>
         
   <plugin id="org.eclipse.datatools.connectivity.apache.derby.nl"  download-size="0" install-size="0" version="0.0.0" fragment="true" unpack="false"/>
   <plugin id="org.eclipse.datatools.connectivity.apache.derby.dbdefinition.nl"  download-size="0" install-size="0" version="0.0.0" fragment="true" unpack="false"/>
   <plugin id="org.eclipse.datatools.connectivity.apache.derby.ui.nl"  download-size="0" install-size="0" version="0.0.0" fragment="true" unpack="false"/>
   <plugin id="org.eclipse.datatools.connectivity.db.generic.nl"  download-size="0" install-size="0" version="0.0.0" fragment="true" unpack="false"/>
   <plugin id="org.eclipse.datatools.connectivity.db.generic.ui.nl"  download-size="0" install-size="0" version="0.0.0" fragment="true" unpack="false"/>
   <plugin id="org.eclipse.datatools.connectivity.dbdefinition.genericJDBC.nl"  download-size="0" install-size="0" version="0.0.0" fragment="true" unpack="false"/>
   <plugin id="org.eclipse.datatools.connectivity.sqm.core.nl"  download-size="0" install-size="0" version="0.0.0" fragment="true" unpack="false"/>
   <plugin id="org.eclipse.datatools.connectivity.sqm.core.ui.nl"  download-size="0" install-size="0" version="0.0.0" fragment="true" unpack="false"/>
   <plugin id="org.eclipse.datatools.connectivity.sqm.server.ui.nl"  download-size="0" install-size="0" version="0.0.0" fragment="true" unpack="false"/>
   <plugin id="org.eclipse.datatools.sqltools.common.ui.nl"  download-size="0" install-size="0" version="0.0.0" fragment="true" unpack="false"/>
   <plugin id="org.eclipse.datatools.sqltools.db.derby.nl"  download-size="0" install-size="0" version="0.0.0" fragment="true" unpack="false"/>
   <plugin id="org.eclipse.datatools.sqltools.db.generic.nl"  download-size="0" install-size="0" version="0.0.0" fragment="true" unpack="false"/>
   <plugin id="org.eclipse.datatools.sqltools.editor.core.nl"  download-size="0" install-size="0" version="0.0.0" fragment="true" unpack="false"/>
   <plugin id="org.eclipse.datatools.sqltools.parsers.sql.nl"  download-size="0" install-size="0" version="0.0.0" fragment="true" unpack="false"/>
   <plugin id="org.eclipse.datatools.sqltools.parsers.sql.query.nl"  download-size="0" install-size="0" version="0.0.0" fragment="true" unpack="false"/>
   <plugin id="org.eclipse.datatools.sqltools.plan.nl"  download-size="0" install-size="0" version="0.0.0" fragment="true" unpack="false"/>
   <plugin id="org.eclipse.datatools.sqltools.result.nl"  download-size="0" install-size="0" version="0.0.0" fragment="true" unpack="false"/>
   <plugin id="org.eclipse.datatools.sqltools.sql.nl"  download-size="0" install-size="0" version="0.0.0" fragment="true" unpack="false"/>
   <plugin id="org.eclipse.datatools.sqltools.sqlbuilder.nl"  download-size="0" install-size="0" version="0.0.0" fragment="true" unpack="false"/>
   <plugin id="org.eclipse.datatools.sqltools.sqleditor.nl"  download-size="0" install-size="0" version="0.0.0" fragment="true" unpack="false"/>
   <plugin id="org.eclipse.datatools.enablement.hsqldb.nl"  download-size="0" install-size="0" version="0.0.0" fragment="true" unpack="false"/>
   <plugin id="org.eclipse.datatools.enablement.hsqldb.dbdefinition.nl"  download-size="0" install-size="0" version="0.0.0" fragment="true" unpack="false"/>
   <plugin id="org.eclipse.datatools.enablement.hsqldb.ui.nl"  download-size="0" install-size="0" version="0.0.0" fragment="true" unpack="false"/>
   <plugin id="org.eclipse.datatools.enablement.ibm.db2.iseries.nl"  download-size="0" install-size="0" version="0.0.0" fragment="true" unpack="false"/>
   <plugin id="org.eclipse.datatools.enablement.ibm.db2.iseries.dbdefinition.nl"  download-size="0" install-size="0" version="0.0.0" fragment="true" unpack="false"/>
   <plugin id="org.eclipse.datatools.enablement.ibm.db2.iseries.ui.nl"  download-size="0" install-size="0" version="0.0.0" fragment="true" unpack="false"/>
   <plugin id="org.eclipse.datatools.enablement.ibm.db2.luw.nl"  download-size="0" install-size="0" version="0.0.0" fragment="true" unpack="false"/>
   <plugin id="org.eclipse.datatools.enablement.ibm.db2.luw.dbdefinition.nl"  download-size="0" install-size="0" version="0.0.0" fragment="true" unpack="false"/>
   <plugin id="org.eclipse.datatools.enablement.ibm.db2.luw.ui.nl"  download-size="0" install-size="0" version="0.0.0" fragment="true" unpack="false"/>
   <plugin id="org.eclipse.datatools.enablement.ibm.db2.zseries.nl"  download-size="0" install-size="0" version="0.0.0" fragment="true" unpack="false"/>
   <plugin id="org.eclipse.datatools.enablement.ibm.db2.zseries.dbdefinition.nl"  download-size="0" install-size="0" version="0.0.0" fragment="true" unpack="false"/>
   <plugin id="org.eclipse.datatools.enablement.ibm.db2.zseries.ui.nl"  download-size="0" install-size="0" version="0.0.0" fragment="true" unpack="false"/>
   <plugin id="org.eclipse.datatools.enablement.ibm.informix.nl"  download-size="0" install-size="0" version="0.0.0" fragment="true" unpack="false"/>
   <plugin id="org.eclipse.datatools.enablement.ibm.informix.dbdefinition.nl"  download-size="0" install-size="0" version="0.0.0" fragment="true" unpack="false"/>
   <plugin id="org.eclipse.datatools.enablement.ibm.informix.ui.nl"  download-size="0" install-size="0" version="0.0.0" fragment="true" unpack="false"/>
   <plugin id="org.eclipse.datatools.enablement.ibm.ui.nl"  download-size="0" install-size="0" version="0.0.0" fragment="true" unpack="false"/>
   <plugin id="org.eclipse.datatools.enablement.msft.sqlserver.nl"  download-size="0" install-size="0" version="0.0.0" fragment="true" unpack="false"/>
   <plugin id="org.eclipse.datatools.enablement.msft.sqlserver.dbdefinition.nl"  download-size="0" install-size="0" version="0.0.0" fragment="true" unpack="false"/>
   <plugin id="org.eclipse.datatools.enablement.msft.sqlserver.ui.nl"  download-size="0" install-size="0" version="0.0.0" fragment="true" unpack="false"/>
   <plugin id="org.eclipse.datatools.enablement.mysql.nl"  download-size="0" install-size="0" version="0.0.0" fragment="true" unpack="false"/>
   <plugin id="org.eclipse.datatools.enablement.mysql.dbdefinition.nl"  download-size="0" install-size="0" version="0.0.0" fragment="true" unpack="false"/>
   <plugin id="org.eclipse.datatools.enablement.mysql.ui.nl"  download-size="0" install-size="0" version="0.0.0" fragment="true" unpack="false"/>
   <plugin id="org.eclipse.datatools.enablement.oracle.nl"  download-size="0" install-size="0" version="0.0.0" fragment="true" unpack="false"/>
   <plugin id="org.eclipse.datatools.enablement.oracle.dbdefinition.nl"  download-size="0" install-size="0" version="0.0.0" fragment="true" unpack="false"/>
   <plugin id="org.eclipse.datatools.enablement.oracle.ui.nl"  download-size="0" install-size="0" version="0.0.0" fragment="true" unpack="false"/>
   <plugin id="org.eclipse.datatools.enablement.postgresql.nl"  download-size="0" install-size="0" version="0.0.0" fragment="true" unpack="false"/>
   <plugin id="org.eclipse.datatools.enablement.postgresql.ui.nl"  download-size="0" install-size="0" version="0.0.0" fragment="true" unpack="false"/>
   <plugin id="org.eclipse.datatools.enablement.sap.maxdb.nl"  download-size="0" install-size="0" version="0.0.0" fragment="true" unpack="false"/>
   <plugin id="org.eclipse.datatools.enablement.sap.maxdb.dbdefinition.nl"  download-size="0" install-size="0" version="0.0.0" fragment="true" unpack="false"/>
   <plugin id="org.eclipse.datatools.enablement.sap.maxdb.ui.nl"  download-size="0" install-size="0" version="0.0.0" fragment="true" unpack="false"/>
   <plugin id="org.eclipse.datatools.enablement.sybase.nl"  download-size="0" install-size="0" version="0.0.0" fragment="true" unpack="false"/>
   <plugin id="org.eclipse.datatools.enablement.sybase.ui.nl"  download-size="0" install-size="0" version="0.0.0" fragment="true" unpack="false"/>
   <plugin id="org.eclipse.datatools.enablement.sybase.asa.nl"  download-size="0" install-size="0" version="0.0.0" fragment="true" unpack="false"/>
   <plugin id="org.eclipse.datatools.enablement.sybase.asa.models.nl"  download-size="0" install-size="0" version="0.0.0" fragment="true" unpack="false"/>
   <plugin id="org.eclipse.datatools.enablement.sybase.ase.dbdefinition.nl"  download-size="0" install-size="0" version="0.0.0" fragment="true" unpack="false"/>
   <plugin id="org.eclipse.datatools.enablement.sybase.ase.profile.nl"  download-size="0" install-size="0" version="0.0.0" fragment="true" unpack="false"/>
         
</feature>
